thetestEyesOnIt/__init__.py
thetestEyesOnIt/eoi_add_stream_inputs.py
thetestEyesOnIt/eoi_monitor_stream_inputs.py
thetestEyesOnIt/eoi_process_image_inputs.py
thetestEyesOnIt/eoi_response.py
thetestEyesOnIt/eoi_stream_url_input.py
thetestEyesOnIt/eoi_utils.py
thetestEyesOnIt/sdk.py
thetestEyesOnIt/elements/__init__.py
thetestEyesOnIt/elements/eoi_alerting.py
thetestEyesOnIt/elements/eoi_bounding_box.py
thetestEyesOnIt/elements/eoi_efficient_detection.py
thetestEyesOnIt/elements/eoi_genetec.py
thetestEyesOnIt/elements/eoi_prompt.py
thetestEyesOnIt/elements/eoi_region.py
thetestEyesOnIt-0.2.0.dist-info/LICENSE.txt
thetestEyesOnIt-0.2.0.dist-info/METADATA
thetestEyesOnIt-0.2.0.dist-info/WHEEL
thetestEyesOnIt-0.2.0.dist-info/top_level.txt
thetestEyesOnIt-0.2.0.dist-info/RECORD
