Metadata-Version: 2.1
Name: thetestEyesOnIt
Version: 0.2.0
Summary: Easy computer vision
Home-page: https://github.com/EyesOnIt-AI/EyesOnIt-python-sdk
Author: EyesOnIt
Author-email: EyesOnIt <info@eyesonit.us>
License: MIT
Requires-Python: >=3.8
License-File: LICENSE.txt
Requires-Dist: pydantic
Requires-Dist: Pillow
Requires-Dist: requests
